chroptiks/__init__.py
chroptiks/plotting_utils.py
chroptiks-0.1.7.dist-info/METADATA
chroptiks-0.1.7.dist-info/WHEEL
chroptiks-0.1.7.dist-info/top_level.txt
chroptiks-0.1.7.dist-info/RECORD
